phonetic_algorithmIPA/__init__.py
phonetic_algorithmIPA/ipa_distances.py
phonetic_algorithmIPA/data/.DS_Store
phonetic_algorithmIPA/data/cons.json
phonetic_algorithmIPA/data/diacrit.json
phonetic_algorithmIPA/data/ftable.json
phonetic_algorithmIPA/data/index_column.json
phonetic_algorithmIPA/data/regs.txt
phonetic_algorithmIPA/data/rows.json
phonetic_algorithmIPA/data/vows.json
phonetic_algorithmIPA-0.2.4.dist-info/METADATA
phonetic_algorithmIPA-0.2.4.dist-info/WHEEL
phonetic_algorithmIPA-0.2.4.dist-info/top_level.txt
phonetic_algorithmIPA-0.2.4.dist-info/RECORD
