Metadata-Version: 2.1
Name: phonetic-algorithmIPA
Version: 0.2.4
Summary: Phonenetic algorithm for IPA
Home-page: UNKNOWN
Author: Anastasiya Kostyanitsyna, George Moroz
Author-email: UNKNOWN
License: UNKNOWN
Platform: UNKNOWN
